gbd/__init__.py
gbd/piptry.py
gbd-0.0.1.dist-info/DESCRIPTION.rst
gbd-0.0.1.dist-info/METADATA
gbd-0.0.1.dist-info/RECORD
gbd-0.0.1.dist-info/WHEEL
gbd-0.0.1.dist-info/metadata.json
gbd-0.0.1.dist-info/top_level.txt
