Metadata-Version: 2.0
Name: gbd
Version: 0.0.1
Summary: Test module
Home-page: https://github.com/rohanneps/rohanneps/tree/master/Scrapper_Test/gbd
Author: Rohan Amatya
Author-email: rohanneps@gmail.com
License: UNKNOWN
Keywords: sample setuptools development
Platform: UNKNOWN
